phpshift/__init__.py
phpshift/main.py
phpshift/.system/imports.py
phpshift/.system/index.py
phpshift/.system/modules/jobs.py
phpshift/.system/sources/clight.json
phpshift/.system/sources/logo.ico
phpshift-1.0.0.dist-info/METADATA
phpshift-1.0.0.dist-info/WHEEL
phpshift-1.0.0.dist-info/entry_points.txt
phpshift-1.0.0.dist-info/top_level.txt
phpshift-1.0.0.dist-info/RECORD
